{
  "name": "Beidou",
  "vision": "Lôi",
  "weapon": "Trọng Kiếm",
  "nation": "Liyue",
  "affiliation": "Đội thuyền Nam Thập Tự",
  "rarity": 4,
  "constellation": "Nam Thiên Hải Sơn",
  "birthday": "0000-02-14",
  "description": "Thủ lĩnh đội thuyền vũ trang \"Nam Thập Tự\", là chị đại hào sảng.",
  "skillTalents": [
    {
      "name": "Đại Dương",
      "unlock": "Tấn Công Thường",
      "description": "Tấn Công Thường\nThực hiện tối đa 5 lần chém liên tiếp.\nTrọng Kích\nDuy trì tiêu hao thể lực, chém nhanh liên tiếp.\n\nSau khi Trọng Kích kết thúc, sẽ bổ một nhát cực mạnh.\nTấn Công Khi Đáp\nĐáp xuống đất từ trên không, tấn công kẻ địch trên đường, đồng thời gây sát thương phạm vi khi chạm đất.",
      "upgrades": [
        {
          "name": "Sát Thương Chém Lần 1",
          "value": "71.1%"
        },
        {
          "name": "Sát Thương Chém Lần 2",
          "value": "70.9%"
        },
        {
          "name": "Sát Thương Chém Lần 3",
          "value": "88.3%"
        },
        {
          "name": "Sát Thương Chém Lần 4",
          "value": "86.5%"
        },
        {
          "name": "Sát Thương Chém Lần 5",
          "value": "112%"
        },
        {
          "name": "Sát Thương Trọng Kích Mỗi Lần Chém",
          "value": "56.2%"
        },
        {
          "name": "Sát Thương Trọng Kích Lần Chém Cuối Cùng",
          "value": "102%"
        },
        {
          "name": "Thể Lực Tiêu Hao Khi Trọng Kích",
          "value": "40/s"
        },
        {
          "name": "Thời Lượng Tối Đa",
          "value": "5s"
        },
        {
          "name": "Sát Thương Tấn Công Khi Đáp",
          "value": "74.6%"
        },
        {
          "name": "Sát Thương Tấn Công Khi Đáp Từ Độ Thấp / Cao",
          "value": "149% / 186%"
        }
      ],
      "type": "NORMAL_ATTACK"
    },
    {
      "name": "Bắt Sóng",
      "unlock": "Kỹ Năng Nguyên Tố",
      "description": "Không có gì phải lo lắng. Nếu có ai dám ra tay với cô hoặc người của cô, thì sẽ phải trả giá gấp 10 lần bằng sấm sét và kiếm.\nNhấn\nTích tụ sức mạnh sấm sét, chém mạnh kiếm lớn về phía trước, gây sát thương Nguyên Tố Lôi.\nNhấn Giữ\nNhấc vũ khí lên hình thành khiên, hấp thụ lượng sát thương căn cứ theo giới hạn HP của Beidou.\n\nSau khi thả giữ kỹ năng hoặc hết thời gian, sẽ vung kiếm giải phóng sức mạnh tích lũy để phản công, gây sát thương Nguyên Tố Lôi. Dựa vào số lần bị tấn công trong thời gian kỹ năng, tăng sát thương tạo thành. Kích hoạt 2 lần sẽ đạt buff sát thương cao nhất.\n\nKhiên có hiệu quả như sau:\n\nĐối với sát thương Nguyên Tố Lôi có 250% hiệu quả hấp thu.\nKhi thi triển, có thêm Nguyên Tố Lôi kèm theo cho Beidou.",
      "upgrades": [
        {
          "name": "Sát Thương Hấp Thụ Từ Khiên",
          "value": "14.4% Max HP + 1386"
        },
        {
          "name": "Base DMG",
          "value": "122%"
        },
        {
          "name": "DMG Bonus on Hit Taken",
          "value": "160%"
        },
        {
          "name": "CD",
          "value": "7.5s"
        }
      ],
      "type": "ELEMENTAL_SKILL"
    },
    {
      "name": "Stormbreaker",
      "unlock": "Elemental Burst",
      "description": "Recalling her slaying of the great beast Haishan. Beidou calls upon that monstrous strength and the lightning to create a Thunderbeast's Targe around herself.\nThunderbeast's Target\n\nWhen Normal and Charged Attacks hit, they create a lightning discharge that can jump between enemies, dealing Electro DMG.\nIncreases the character's resistance to interruption, and decreases DMG taken.\n",
      "upgrades": [
        {
          "name": "Skill DMG",
          "value": "122%"
        },
        {
          "name": "Lightning DMG",
          "value": "96%"
        },
        {
          "name": "DMG Reduction",
          "value": "20%"
        },
        {
          "name": "Duration",
          "value": "15s"
        },
        {
          "name": "CD",
          "value": "20s"
        },
        {
          "name": "Energy Cost",
          "value": "80"
        }
      ],
      "type": "ELEMENTAL_BURST"
    }
  ],
  "passiveTalents": [
    {
      "name": "Retribution",
      "unlock": "Unlocked at Ascension 1",
      "description": "Counterattacking with Tidecaller at the precise moment when the character is hit grants the maximum DMG Bonus.",
      "level": 1
    },
    {
      "name": "Leviathan's Protection",
      "unlock": "Unlocked at Ascension 4",
      "description": "Gain the following effects for 10s after unleashing Tidecaller with its maximum DMG Bonus:\nDMG dealt by Normal and Charged Attacks is increased by 15%. ATK SPD of Normal and Charged Attacks is increased by 15%.\nGreatly reduced delay before unleashing Charged Attacks.",
      "level": 4
    },
    {
      "name": "Conqueror of Tides",
      "unlock": "Unlocked Automatically",
      "description": "Decreases all party member's swimming Stamina consumption by 20%."
    }
  ],
  "constellations": [
    {
      "name": "Sea Beast's Scourge",
      "unlock": "Constellation Lv. 1",
      "description": "When Stormbreaker is used:\nCreates a shield that absorbs up to 16% of Beidou's Max HP for 15s.\nThis shield absorbs Electro DMG 250% more effectively.",
      "level": 1
    },
    {
      "name": "Upon the Turbulent Sea, the Thunder Arises",
      "unlock": "Constellation Lv. 2",
      "description": "Stormbreaker's arc lightning can jump 2 additional targets.",
      "level": 2
    },
    {
      "name": "Summoner of Storm",
      "unlock": "Constellation Lv. 3",
      "description": "Increases the Level of Tidecaller by 3.\nMaximum upgrade level is 15.",
      "level": 3
    },
    {
      "name": "Stunning Revenge",
      "unlock": "Constellation Lv. 4",
      "description": "Within 10s of taking DMG, Beidou's Normal Attacks gain 20% additional Electro DMG.",
      "level": 4
    },
    {
      "name": "Crimson Tidewalker",
      "unlock": "Constellation Lv. 5",
      "description": "Increase the Level of Stormbreaker by 3.\nMaximum upgrade level is 15.",
      "level": 5
    },
    {
      "name": "Bane of Evil",
      "unlock": "Constellation Lv. 6",
      "description": "During the duration of Stormbreaker, the Electro RES of surrounding enemies is decreased by 15%.",
      "level": 6
    }
  ],
  "vision_key": "ELECTRO",
  "weapon_type": "CLAYMORE"
}
